README.md
setup.cfg
setup.py
django_flash_rest.egg-info/PKG-INFO
django_flash_rest.egg-info/SOURCES.txt
django_flash_rest.egg-info/dependency_links.txt
django_flash_rest.egg-info/requires.txt
django_flash_rest.egg-info/top_level.txt
flash_rest/__init__.py
flash_rest/permissions.py
flash_rest/decorators/__init__.py
flash_rest/decorators/utils.py
flash_rest/deserializers/__init__.py
flash_rest/deserializers/base.py
flash_rest/exceptions/__init__.py
flash_rest/http/__init__.py
flash_rest/http/exceptions.py
flash_rest/http/methods.py
flash_rest/http/status.py
flash_rest/serializers/__init__.py
flash_rest/serializers/base.py
flash_rest/serializers/exceptions.py
flash_rest/serializers/fields.py
flash_rest/serializers/serializers.py